mbed_tools_lib/__init__.py
mbed_tools_lib/_version.py
mbed_tools_lib/exceptions.py
mbed_tools_lib/logging.py
mbed_tools_lib/python_helpers.py
mbed_tools_lib/_internal/__init__.py
mbed_tools_lib-1.2.1.dist-info/LICENSE
mbed_tools_lib-1.2.1.dist-info/METADATA
mbed_tools_lib-1.2.1.dist-info/WHEEL
mbed_tools_lib-1.2.1.dist-info/top_level.txt
mbed_tools_lib-1.2.1.dist-info/RECORD
